django_apsw/placeholder.py
django_apsw-0.1.0a0.dist-info/LICENSE
django_apsw-0.1.0a0.dist-info/METADATA
django_apsw-0.1.0a0.dist-info/WHEEL
django_apsw-0.1.0a0.dist-info/RECORD
