Metadata-Version: 2.1
Name: django-apsw
Version: 0.1.0a0
Summary: Django database backend for SQLite using the APSW driver
License: MIT
Keywords: django,apsw,database,backend,sqlite
Author: Armand Rego
Author-email: armand@weirdsheeplabs.com
Requires-Python: >=3.9,<4.0
Classifier: Development Status :: 2 - Pre-Alpha
Classifier: Intended Audience :: Developers
Classifier: License :: OSI Approved :: MIT License
Classifier: Programming Language :: Python :: 3
Classifier: Programming Language :: Python :: 3.9
Classifier: Programming Language :: Python :: 3.10
Classifier: Programming Language :: Python :: 3.11
Classifier: Programming Language :: Python :: 3.12
Requires-Dist: apsw (>=3.45.2.0,<4.0.0.0)
Requires-Dist: django (>=4.2,<5.0)
